[{"web_entities": [{"entity_id": "/m/062cnx", "score": 5.622000217437744, "description": "Steve Doocy"}, {"entity_id": "/m/09p7pv", "score": 0.7477499842643738, "description": "Fox & Friends"}, {"entity_id": "/t/2cf506h2f2h10", "score": 0.7116000056266785, "description": ""}, {"entity_id": "/m/02z_b", "score": 0.7116000056266785, "description": "Fox News"}, {"entity_id": "/m/0d8qb", "score": 0.683899998664856, "description": "Journalist"}, {"entity_id": "/m/02plw45", "score": 0.4916999936103821, "description": "Jacques Steinberg"}, {"entity_id": "/m/09c7w0", "score": 0.44085001945495605, "description": "United States"}, {"entity_id": "/t/26tx7xy9_tgvr", "score": 0.40049999952316284, "description": ""}, {"entity_id": "/g/11f0z25nkf", "score": 0.3765999972820282, "description": ""}, {"entity_id": "/m/068jd", "score": 0.34610000252723694, "description": "Photograph"}], "pages_with_matching_images": [{"url": "https://www.dailykos.com/story/2008/7/3/545865/-"}, {"url": "https://twitter.com/MattGertz/status/1057332248633098240"}, {"url": "https://threadreaderapp.com/thread/1057332248633098240.html"}, {"url": "http://hoaxes.org/photo_database/image/fox_airs_faux_photos"}, {"url": "https://twitter.com/mattgertz/status/1057332248633098240?lang=bg"}, {"url": "https://www.businessinsider.com.au/fox-news-we-photoshop-you-decide-2008-7"}, {"url": "http://dailycandor.com/fox-news-well-make-you-look-ugly-if-we-dont-like-you/"}, {"url": "https://www.trendhunter.com/trends/photoshopping-for-evil-fox-news-makes-ny-times-reporters-ugly"}, {"url": "http://dailycandor.com/2008/07/page/2/"}, {"url": "https://twitter.com/mattgertz/status/1105169155324592128?lang=en"}], "full_matching_images": [{"url": "http://hoaxmuseumimages.s3.amazonaws.com/2008foxnews_thumb.jpg"}], "partial_matching_images": [{"url": "http://i.imgur.com/gnSx7.png"}, {"url": "https://qph.fs.quoracdn.net/main-qimg-86ade00d416d548591287f7ad15dd3b6.webp"}, {"url": "https://66.media.tumblr.com/6d3b5ea35a0617abfb2c6ae249c3b2e8/tumblr_inline_oq5s9enzyb1qzc68q_500.jpg"}, {"url": "https://i0.wp.com/dailycandor.com/wp-content/uploads/2008/07/fox-20080702-reddicliffe.jpg?resize=400%2C335"}, {"url": "https://i12.photobucket.com/albums/a229/dhonig2/fox-20080702-steinberg.jpg"}, {"url": "https://i0.wp.com/dailycandor.com/wp-content/uploads/2008/07/fox-20080702-steinberg.jpg?resize=400%2C335"}, {"url": "http://i.imgur.com/OPbY2.jpg"}, {"url": "http://i.imgur.com/FMhFz.jpg"}, {"url": "https://pbs.twimg.com/media/D1Zv_jPXcAA3IS_.jpg"}, {"url": "https://pbs.twimg.com/media/D1ZZehNXgAAS5jt.jpg"}]}]