[{"web_entities": [{"entity_id": "/m/02kyd8", "score": 0.7032999992370605, "description": "Political campaign"}, {"entity_id": "/m/02jnr7", "score": 0.6499999761581421, "description": "John Kerry 2004 presidential campaign"}, {"entity_id": "/m/04qwhs", "score": 0.6348000168800354, "description": "2004 United States presidential election"}, {"entity_id": "/m/068jd", "score": 0.6316999793052673, "description": "Photograph"}, {"entity_id": "/m/0jg24", "score": 0.5157999992370605, "description": "Image"}, {"entity_id": "/m/05qt0", "score": 0.3450999855995178, "description": "Politics"}, {"entity_id": "/m/02l3h", "score": 0.33889999985694885, "description": "Election"}, {"entity_id": "/m/0dq_n", "score": 0.31790000200271606, "description": "Hoax"}, {"entity_id": "/m/02jxtf", "score": 0.310699999332428, "description": "George W. Bush 2004 presidential campaign"}, {"entity_id": "/m/07c52", "score": 0.27869999408721924, "description": "Television"}], "pages_with_matching_images": [{"url": "http://hoaxes.org/photo_database/image/whatever_it_takes"}, {"url": "http://hoaxes.org/photo_database/fulltext/P80"}, {"url": "http://hoaxes.org/photo_database/chronological/P80"}, {"url": "http://hoaxes.org/photo_database/photo_category/category./P54"}, {"url": "http://www.roscherdesigns.com/tag/political/"}, {"url": "https://www.roscherdesigns.com/tag/fails/"}, {"url": "http://www.roscherdesigns.com/tag/photoshop/"}, {"url": "https://www.roscherdesigns.com/photos-that-will-make-you-laugh/"}, {"url": "http://despadanicom.blogspot.com/2011/03/photoshop-tricks-10-historic-political.html"}, {"url": "https://www.cc.gatech.edu/~beki/cs4001/history.pdf"}], "full_matching_images": [{"url": "http://cdn5.upsocl.com/wp-content/uploads/2016/03/georgebush1_370x278.jpg"}, {"url": "https://cbsnews2.cbsistatic.com/hub/i/r/2011/05/10/57ff9d23-a643-11e2-a3f0-029118418759/resize/620x465/d92f7eb31a180df93d46f1d06aef7ef5/georgebush1_370x278.jpg"}, {"url": "http://img4.itiexue.net/1912/19121836.jpg"}, {"url": "https://tc.sinaimg.cn/maxwidth.800/tc.service.weibo.com/mmbiz_qlogo_cn/c806695f034965211517645e4a162a2a.jpg"}, {"url": "http://www.sinaimg.cn/dy/slidenews/61_img/2015_30/40602_1242741_510220.jpg"}, {"url": "https://i1.kknews.cc/SIG=uei5q8/12500000p4no5q871098.jpg"}, {"url": "http://a0.att.hudong.com/17/96/300000868259129193964027671_950.jpg"}, {"url": "http://n1.itc.cn/img8/wb/smccloud/2015/04/29/143030778209229266.JPEG"}, {"url": "http://image.zdnet.co.kr/2011/05/07/IiJoKtZnO0nqWmvVMlka.jpg"}, {"url": "http://hoaxmuseumimages.s3.amazonaws.com/2004bushad_thumb.jpg"}], "partial_matching_images": [{"url": "https://images.boredomfiles.com/wp-content/uploads/sites/9/2017/12/clones-1.jpg"}, {"url": "https://slideplayer.se/slide/1987554/7/images/18/Forts%C3%A4ttning.jpg"}, {"url": "https://images.slideplayer.com/13/3927047/slides/slide_14.jpg"}, {"url": "https://image.slidesharecdn.com/cfakepath090623-091112060019-phpapp02/95/-30-728.jpg?cb=1278728111"}, {"url": "https://img.chinatimes.com/newsphoto/2015-09-30/656/20150930004179.jpg"}, {"url": "https://i0.wp.com/militaryhistorynow.com/wp-content/uploads/2014/06/georgebush2.jpg?resize=560%2C427&ssl=1"}, {"url": "http://geeksroom.com/wp-content/uploads/2010/09/manipulacion_fotografica_politica-07.jpg"}, {"url": "https://i1.wp.com/geeksroom.com/wp-content/uploads/2010/09/manipulacion_fotografica_politica-07b.jpg?resize=365%2C555"}, {"url": "http://column.ccsph.com/uploadfiles/images/20141113/1113022129684605.jpg"}, {"url": "http://p9.pstatp.com/large/pgc-image/15376871994225ed7b70462"}]}]