[{"web_entities": [{"entity_id": "/m/02l00m", "score": 0.7243000268936157, "description": "Sun spiders"}, {"entity_id": "/m/01x_v", "score": 0.6359999775886536, "description": "Camel"}, {"entity_id": "/m/0755b", "score": 0.42989999055862427, "description": "Scorpion"}, {"entity_id": "/m/0zkm", "score": 0.38749998807907104, "description": "Arthropod"}, {"entity_id": "/m/07t70", "score": 0.3691999912261963, "description": "Urban legend"}, {"entity_id": "/m/0d05q4", "score": 0.35144999623298645, "description": "Iraq"}, {"entity_id": "/m/0284w", "score": 0.34450000524520874, "description": "Desert"}, {"entity_id": "/m/03skld", "score": 0.3190000057220459, "description": "Goliath birdeater"}, {"entity_id": "/m/09kmb", "score": 0.23882099986076355, "description": "Spider"}, {"entity_id": "/g/11f5rmcwrd", "score": 0.22509999573230743, "description": "False Spiders"}], "pages_with_matching_images": [{"url": "https://www.snopes.com/fact-check/camel-spiders/"}, {"url": "https://www.thoughtco.com/attack-of-the-camel-spiders-3299801"}, {"url": "http://www.camel-spiders.net/"}, {"url": "http://skunksoup.com/2011/09/just-for-fun/photos/giant-camel-spiders-in-iraqi-desert-picture-video"}, {"url": "http://www.camel-spiders.net/faq.php"}, {"url": "http://www.hoax-slayer.com/camel-spider-hoax-email.html"}, {"url": "http://www.livingwithbugs.com/camel_sp.html"}, {"url": "http://uncyclopedia.wikia.com/wiki/Camel_spider"}, {"url": "https://imgur.com/gallery/7VVqh"}, {"url": "http://www.unexplainedmonsters.com/monster_spiders/camel_spiders.html"}], "full_matching_images": [{"url": "https://dmad193.files.wordpress.com/2014/01/22.jpg"}, {"url": "http://gallery2.persiangig.com/images/Spiders/Spiders_1004.jpg"}, {"url": "http://www.digitaljournal.com/img/2/1/0/8/2/9/i/3/9/7/o/camel_spider.jpg"}, {"url": "http://3.bp.blogspot.com/-hDPyq-a_iW8/UhQRlLZD4lI/AAAAAAAAAkw/ZEpGo-7C0EE/s1600/camel_spider.jpg"}, {"url": "http://www.krisenkommandokraefte.de/intern/bild_der_woche/36.jpg"}, {"url": "http://cdn.animalhi.com/1600x1200/20121101/camel%20spider%201600x1200%20wallpaper_www.animalhi.com_67.jpg"}, {"url": "https://www.meoso.com/wp-content/uploads/2011/12/wolf-spider.jpg"}, {"url": "https://www.touslesjourscurieux.fr/wp-content/uploads/2019/01/09-1.jpg"}, {"url": "https://img-4.linternaute.com/rLe4b7OuKs2823wB0tSjKDRuIys=/1240x/smart/77e96310cfe447ae95a994a4dfc0920b/ccmcms-linternaute/2321424.jpg"}, {"url": "http://medias.digitamix.com/10240/les-15-photos-truquees-les-plus-celebres-et-souvent-prises-au-serieux-243582.jpg"}], "partial_matching_images": [{"url": "http://vardayok.club/wp-content/uploads//2018/07/pet-camel-spiders-camel-spider-found-in-worksheet-works-word-search.jpg"}, {"url": "http://inews.gtimg.com/newsapp_match/0/1820955944/0"}, {"url": "http://persianpet.org/forum/images/imported/2008/08/1974.jpg"}, {"url": "http://s3-sa-east-1.amazonaws.com/mundogum/wp-content/uploads/2007/02/insect_desert-1.jpg"}, {"url": "https://cdn2.lamp.im/wp-content/uploads/2018/02/falsh-7.jpg"}, {"url": "https://cdn3.coconutsky.club/wp-content/uploads/2018/04/10-143.jpg"}, {"url": "http://4.bp.blogspot.com/-0_spAZK4b2s/Uo-4_P-YcwI/AAAAAAAA9OY/Vy1SN9MubOo/s1600/13_44_30_687_file.jpeg"}, {"url": "http://national-travel.ru/images/photos/medium/afganskaya-falanga-597ce08a7420a.jpg"}, {"url": "https://t1.daumcdn.net/cfile/tistory/193F7749504072090E"}, {"url": "http://img.photoprikol.net/2011-05/1306607012_ochen-bolshoy-pauk.jpg"}]}]